pycocotools-stubs/METADATA.toml
pycocotools-stubs/__init__.pyi
pycocotools-stubs/coco.pyi
pycocotools-stubs/cocoeval.pyi
pycocotools-stubs/mask.pyi
pycocotools-stubs/py.typed
types_pycocotools-2.0.0.20250809.dist-info/licenses/LICENSE
types_pycocotools-2.0.0.20250809.dist-info/METADATA
types_pycocotools-2.0.0.20250809.dist-info/WHEEL
types_pycocotools-2.0.0.20250809.dist-info/top_level.txt
types_pycocotools-2.0.0.20250809.dist-info/RECORD
